[
  {
    "domain": ".instagram.com",
    "expirationDate": 1774313606,
    "hostOnly": false,
    "httpOnly": false,
    "name": "dpr",
    "path": "/",
    "sameSite": "no_restriction",
    "secure": true,
    "session": false,
    "storeId": "0",
    "value": "1.25"
  },
  {
    "domain": ".instagram.com",
    "expirationDate": 1808206332.547202,
    "hostOnly": false,
    "httpOnly": true,
    "name": "datr",
    "path": "/",
    "sameSite": "no_restriction",
    "secure": true,
    "session": false,
    "storeId": "0",
    "value": "_LG3aePCU0QRzqzL8AiVd7bC"
  },
  {
    "domain": ".instagram.com",
    "expirationDate": 1805182332.547318,
    "hostOnly": false,
    "httpOnly": true,
    "name": "ig_did",
    "path": "/",
    "sameSite": "no_restriction",
    "secure": true,
    "session": false,
    "storeId": "0",
    "value": "1C23C6D3-BC3A-46ED-82EB-E9633CB1778A"
  },
  {
    "domain": ".instagram.com",
    "expirationDate": 1808206332.547407,
    "hostOnly": false,
    "httpOnly": true,
    "name": "mid",
    "path": "/",
    "sameSite": "no_restriction",
    "secure": true,
    "session": false,
    "storeId": "0",
    "value": "abex_AALAAEY3b8BTo77uylA_tAN"
  },
  {
    "domain": ".instagram.com",
    "expirationDate": 1805182400.056513,
    "hostOnly": false,
    "httpOnly": false,
    "name": "ig_nrcb",
    "path": "/",
    "sameSite": "unspecified",
    "secure": true,
    "session": false,
    "storeId": "0",
    "value": "1"
  },
  {
    "domain": ".instagram.com",
    "expirationDate": 1808250463.758559,
    "hostOnly": false,
    "httpOnly": true,
    "name": "ps_l",
    "path": "/",
    "sameSite": "lax",
    "secure": true,
    "session": false,
    "storeId": "0",
    "value": "1"
  },
  {
    "domain": ".instagram.com",
    "expirationDate": 1808250463.758792,
    "hostOnly": false,
    "httpOnly": true,
    "name": "ps_n",
    "path": "/",
    "sameSite": "no_restriction",
    "secure": true,
    "session": false,
    "storeId": "0",
    "value": "1"
  },
  {
    "domain": ".instagram.com",
    "expirationDate": 1808273322.289304,
    "hostOnly": false,
    "httpOnly": false,
    "name": "csrftoken",
    "path": "/",
    "sameSite": "unspecified",
    "secure": true,
    "session": false,
    "storeId": "0",
    "value": "saq2N5xHSYSuEqdr1E3UDzg46oT9l6vW"
  },
  {
    "domain": ".instagram.com",
    "expirationDate": 1781489322.289616,
    "hostOnly": false,
    "httpOnly": false,
    "name": "ds_user_id",
    "path": "/",
    "sameSite": "no_restriction",
    "secure": true,
    "session": false,
    "storeId": "0",
    "value": "56750085587"
  },
  {
    "domain": ".instagram.com",
    "expirationDate": 1805249313.056751,
    "hostOnly": false,
    "httpOnly": true,
    "name": "sessionid",
    "path": "/",
    "sameSite": "no_restriction",
    "secure": true,
    "session": false,
    "storeId": "0",
    "value": "56750085587%3AQ68SaMW3u0CmVw%3A27%3AAYjXt0liN4hNecQDf4Xue4NkDL7HaKwzNKRR-wNiRA"
  },
  {
    "domain": ".instagram.com",
    "expirationDate": 1774318119,
    "hostOnly": false,
    "httpOnly": false,
    "name": "wd",
    "path": "/",
    "sameSite": "lax",
    "secure": true,
    "session": false,
    "storeId": "0",
    "value": "1179x911"
  },
  {
    "domain": ".instagram.com",
    "hostOnly": false,
    "httpOnly": true,
    "name": "rur",
    "path": "/",
    "sameSite": "lax",
    "secure": true,
    "session": true,
    "storeId": "0",
    "value": "\"RVA\\05456750085587\\0541805249322:01feaa49acdc8f6d8ad41801abf82a3f609a73aa9a8819e1a00fd95b70fec48cce8c5f36\""
  }
]
